ceshigfzd_C/__init__.py
ceshigfzd_C/calculate.cpython-311-darwin.so
ceshigfzd_C-0.1.dist-info/LICENSE.txt
ceshigfzd_C-0.1.dist-info/METADATA
ceshigfzd_C-0.1.dist-info/WHEEL
ceshigfzd_C-0.1.dist-info/top_level.txt
ceshigfzd_C-0.1.dist-info/RECORD
