Metadata-Version: 2.1
Name: ceshigfzd-C
Version: 0.1
Summary: lixintong shi shabi
Author: Your Name
Author-email: your.email@example.com
Classifier: Programming Language :: Python :: 3
Classifier: License :: OSI Approved :: MIT License
Classifier: Operating System :: OS Independent
Requires-Python: >=3.6
License-File: LICENSE.txt
Requires-Dist: pandas
Requires-Dist: openpyxl
